{"isOutlineOf":"W22276","nodes":[{"id":"O01CT00299984","beginsAt":3,"volume":19,"endsAt":33,"title":["དཔལ་སྒྲའི་སྙེ་མ་དུ་མའི་དོན་ཤེས་ཤིང་རྟོགས་པ།"]},{"id":"O01CT00299985","beginsAt":35,"volume":19,"endsAt":71,"title":["བརྡ་སྤྲོད་དབྱངས་ཅན་གྱི་མདོ།"]},{"id":"O01CT00299986","beginsAt":71,"volume":19,"endsAt":717,"title":["དབྱངས་ཅན་བརྡ་སྤྲོད་ཀྱི་འགྲེལ་པ་མཆོག་ཏུ་གསལ་བ།"]},{"id":"O01CT002901MS276","beginsAt":719,"volume":19,"endsAt":725},{"id":"O01CT0029d1e1737","beginsAt":9,"volume":13,"endsAt":26},{"id":"O01CT0029d1e1788","beginsAt":233,"volume":13,"endsAt":252},{"id":"O01CT0029d1e1798","beginsAt":253,"volume":13,"endsAt":277},{"id":"O01CT0029d1e1849","beginsAt":471,"volume":13,"endsAt":602},{"id":"O01CT0029d1e1819","beginsAt":287,"volume":13,"endsAt":368},{"id":"O01CT0029d1e1839","beginsAt":395,"volume":13,"endsAt":469},{"id":"O01CT0029d1e1809","beginsAt":279,"volume":13,"endsAt":286},{"id":"O01CT0029d1e1748","beginsAt":27,"volume":13,"endsAt":62},{"id":"O01CT0029d1e1880","beginsAt":671,"volume":13,"endsAt":719},{"id":"O01CT0029d1e1870","beginsAt":667,"volume":13,"endsAt":669},{"id":"O01CT0029d1e1758","beginsAt":63,"volume":13,"endsAt":92},{"id":"O01CT0029d1e1829","beginsAt":369,"volume":13,"endsAt":393},{"id":"O01CT0029d1e1859","beginsAt":603,"volume":13,"endsAt":666},{"id":"O01CT0029d1e1910","beginsAt":807,"volume":13,"endsAt":822},{"id":"O01CT0029d1e1890","beginsAt":721,"volume":13,"endsAt":737},{"id":"O01CT0029d1e1900","beginsAt":739,"volume":13,"endsAt":805},{"id":"O01CT0029d1e1778","beginsAt":153,"volume":13,"endsAt":231},{"id":"O01CT0029d1e1768","beginsAt":93,"volume":13,"endsAt":151},{"id":"O01CT0029d1e1920","beginsAt":823,"volume":13,"endsAt":834},{"id":"O01CT0029d1e1931","beginsAt":835,"volume":13,"endsAt":843},{"id":"O01CT0029d1e599","beginsAt":251,"volume":6,"endsAt":283},{"id":"O01CT0029d1e609","beginsAt":285,"volume":6,"endsAt":343},{"id":"O01CT0029d1e578","beginsAt":171,"volume":6,"endsAt":231},{"id":"O01CT0029d1e619","beginsAt":345,"volume":6,"endsAt":351},{"id":"O01CT0029d1e711","beginsAt":659,"volume":6,"endsAt":697},{"id":"O01CT0029d1e680","beginsAt":529,"volume":6,"endsAt":574},{"id":"O01CT0029d1e660","beginsAt":435,"volume":6,"endsAt":458},{"id":"O01CT0029d1e721","beginsAt":699,"volume":6,"endsAt":709},{"id":"O01CT0029d1e700","beginsAt":609,"volume":6,"endsAt":658},{"id":"O01CT0029d1e548","beginsAt":7,"volume":6,"endsAt":143},{"id":"O01CT0029d1e629","beginsAt":353,"volume":6,"endsAt":371},{"id":"O01CT0029d1e639","beginsAt":371,"volume":6,"endsAt":415},{"id":"O01CT0029d1e670","beginsAt":459,"volume":6,"endsAt":527},{"id":"O01CT0029d1e690","beginsAt":575,"volume":6,"endsAt":607},{"id":"O01CT0029d1e731","beginsAt":713,"volume":6,"endsAt":717},{"id":"O01CT0029d1e741","beginsAt":717,"volume":6,"endsAt":726},{"id":"O01CT0029d1e589","beginsAt":233,"volume":6,"endsAt":249},{"id":"O01CT0029d1e568","beginsAt":153,"volume":6,"endsAt":170},{"id":"O01CT0029d1e650","beginsAt":419,"volume":6,"endsAt":433},{"id":"O01CT0029d1e558","beginsAt":145,"volume":6,"endsAt":152},{"id":"O01CT0029d1e751","beginsAt":727,"volume":6,"endsAt":935},{"id":"O01CT0029d1e883","beginsAt":833,"volume":7,"endsAt":877},{"id":"O01CT0029d1e812","beginsAt":261,"volume":7,"endsAt":332},{"id":"O01CT0029d1e772","beginsAt":45,"volume":7,"endsAt":54},{"id":"O01CT0029d1e924","beginsAt":951,"volume":7,"endsAt":955},{"id":"O01CT0029d1e802","beginsAt":211,"volume":7,"endsAt":260},{"id":"O01CT0029d1e914","beginsAt":945,"volume":7,"endsAt":949},{"id":"O01CT0029d1e792","beginsAt":107,"volume":7,"endsAt":210},{"id":"O01CT0029d1e853","beginsAt":661,"volume":7,"endsAt":713},{"id":"O01CT0029d1e965","beginsAt":1013,"volume":7,"endsAt":1023},{"id":"O01CT0029d1e944","beginsAt":977,"volume":7,"endsAt":986},{"id":"O01CT0029d1e955","beginsAt":989,"volume":7,"endsAt":1011},{"id":"O01CT0029d1e822","beginsAt":333,"volume":7,"endsAt":362},{"id":"O01CT0029d1e833","beginsAt":363,"volume":7,"endsAt":389},{"id":"O01CT0029d1e894","beginsAt":877,"volume":7,"endsAt":931},{"id":"O01CT0029d1e761","beginsAt":7,"volume":7,"endsAt":41},{"id":"O01CT0029d1e934","beginsAt":957,"volume":7,"endsAt":973},{"id":"O01CT0029d1e863","beginsAt":713,"volume":7,"endsAt":783},{"id":"O01CT0029d1e873","beginsAt":785,"volume":7,"endsAt":832},{"id":"O01CT0029d1e843","beginsAt":391,"volume":7,"endsAt":661},{"id":"O01CT0029d1e975","beginsAt":1025,"volume":7,"endsAt":1028},{"id":"O01CT0029d1e904","beginsAt":933,"volume":7,"endsAt":944},{"id":"O01CT0029d1e782","beginsAt":55,"volume":7,"endsAt":105},{"id":"O01CT0029d1e29","beginsAt":717,"volume":1,"endsAt":724},{"id":"O01CT0029d1e192DB671762DB67177","beginsAt":697,"volume":1,"endsAt":715},{"id":"O01CT0029d1e9","beginsAt":7,"volume":1,"endsAt":675},{"id":"O01CT0029d1e50","beginsAt":1001,"volume":1,"endsAt":1007},{"id":"O01CT0029d1e40","beginsAt":725,"volume":1,"endsAt":999},{"id":"O01CT0029d1e19","beginsAt":685,"volume":1,"endsAt":696},{"id":"O01CT0029d1e60","beginsAt":1009,"volume":1,"endsAt":1019},{"id":"O01CT002901MS1","beginsAt":677,"volume":1,"endsAt":683},{"id":"O01CT0029d1e2368","beginsAt":895,"volume":14,"endsAt":913},{"id":"O01CT0029d1e2347","beginsAt":855,"volume":14,"endsAt":859},{"id":"O01CT0029d1e2317","beginsAt":825,"volume":14,"endsAt":837},{"id":"O01CT0029d1e2388","beginsAt":925,"volume":14,"endsAt":957},{"id":"O01CT0029d1e2246","beginsAt":661,"volume":14,"endsAt":691},{"id":"O01CT0029d1e2063","beginsAt":315,"volume":14,"endsAt":331},{"id":"O01CT0029d1e2398","beginsAt":959,"volume":14,"endsAt":964},{"id":"O01CT0029d1e2276","beginsAt":717,"volume":14,"endsAt":762},{"id":"O01CT0029d1e2042","beginsAt":301,"volume":14,"endsAt":306},{"id":"O01CT0029d1e2124","beginsAt":397,"volume":14,"endsAt":401},{"id":"O01CT0029d1e2032","beginsAt":283,"volume":14,"endsAt":300},{"id":"O01CT0029d1e2154","beginsAt":421,"volume":14,"endsAt":424},{"id":"O01CT0029d1e2002","beginsAt":243,"volume":14,"endsAt":247},{"id":"O01CT0029d1e2337","beginsAt":847,"volume":14,"endsAt":853},{"id":"O01CT0029d1e2266","beginsAt":711,"volume":14,"endsAt":715},{"id":"O01CT0029d1e2185","beginsAt":499,"volume":14,"endsAt":517},{"id":"O01CT0029d1e1951","beginsAt":29,"volume":14,"endsAt":36},{"id":"O01CT0029d1e1992","beginsAt":193,"volume":14,"endsAt":241},{"id":"O01CT0029d1e2236","beginsAt":607,"volume":14,"endsAt":660},{"id":"O01CT0029d1e1971","beginsAt":131,"volume":14,"endsAt":135},{"id":"O01CT0029d1e2195","beginsAt":519,"volume":14,"endsAt":546},{"id":"O01CT0029d1e2215","beginsAt":563,"volume":14,"endsAt":569},{"id":"O01CT0029d1e2256","beginsAt":693,"volume":14,"endsAt":710},{"id":"O01CT0029d1e2114","beginsAt":375,"volume":14,"endsAt":396},{"id":"O01CT0029d1e2175","beginsAt":427,"volume":14,"endsAt":497},{"id":"O01CT0029d1e2073","beginsAt":333,"volume":14,"endsAt":343},{"id":"O01CT0029d1e2144","beginsAt":405,"volume":14,"endsAt":420},{"id":"O01CT0029d1e2358","beginsAt":861,"volume":14,"endsAt":893},{"id":"O01CT0029d1e2012","beginsAt":249,"volume":14,"endsAt":259},{"id":"O01CT0029d1e2022","beginsAt":261,"volume":14,"endsAt":281},{"id":"O01CT0029d1e2327","beginsAt":837,"volume":14,"endsAt":846},{"id":"O01CT0029d1e2378","beginsAt":915,"volume":14,"endsAt":923},{"id":"O01CT0029d1e2297","beginsAt":781,"volume":14,"endsAt":813},{"id":"O01CT0029d1e2286","beginsAt":763,"volume":14,"endsAt":780},{"id":"O01CT002901MS207","beginsAt":37,"volume":14,"endsAt":89},{"id":"O01CT0029d1e2307","beginsAt":815,"volume":14,"endsAt":824},{"id":"O01CT0029d1e2103","beginsAt":363,"volume":14,"endsAt":373},{"id":"O01CT0029d1e1961","beginsAt":91,"volume":14,"endsAt":129},{"id":"O01CT0029d1e2225","beginsAt":571,"volume":14,"endsAt":606},{"id":"O01CT0029d1e1941","beginsAt":11,"volume":14,"endsAt":28},{"id":"O01CT0029d1e1981","beginsAt":137,"volume":14,"endsAt":191},{"id":"O01CT0029d1e2205","beginsAt":547,"volume":14,"endsAt":561},{"id":"O01CT0029d1e2164","beginsAt":425,"volume":14,"endsAt":426},{"id":"O01CT0029d1e2134","beginsAt":403,"volume":14,"endsAt":404},{"id":"O01CT0029d1e2053","beginsAt":307,"volume":14,"endsAt":313},{"id":"O01CT0029d1e2093","beginsAt":357,"volume":14,"endsAt":362},{"id":"O01CT0029d1e2083","beginsAt":345,"volume":14,"endsAt":355},{"id":"O01CT0029d1e2520","beginsAt":281,"volume":17,"endsAt":322},{"id":"O01CT0029d1e2622","beginsAt":787,"volume":17,"endsAt":898},{"id":"O01CT0029d1e2663","beginsAt":1013,"volume":17,"endsAt":1019},{"id":"O01CT0029d1e2530","beginsAt":323,"volume":17,"endsAt":335},{"id":"O01CT0029d1e2581","beginsAt":419,"volume":17,"endsAt":537},{"id":"O01CT0029d1e2490","beginsAt":7,"volume":17,"endsAt":163},{"id":"O01CT0029d1e2652","beginsAt":983,"volume":17,"endsAt":1012},{"id":"O01CT0029d1e2500","beginsAt":165,"volume":17,"endsAt":248},{"id":"O01CT0029d1e2541","beginsAt":337,"volume":17,"endsAt":360},{"id":"O01CT0029d1e2551","beginsAt":361,"volume":17,"endsAt":364},{"id":"O01CT0029d1e2632","beginsAt":899,"volume":17,"endsAt":945},{"id":"O01CT0029d1e2683","beginsAt":1039,"volume":17,"endsAt":1063},{"id":"O01CT0029d1e2673","beginsAt":1021,"volume":17,"endsAt":1038},{"id":"O01CT0029d1e2571","beginsAt":373,"volume":17,"endsAt":417},{"id":"O01CT0029d1e2602","beginsAt":573,"volume":17,"endsAt":759},{"id":"O01CT0029d1e2510","beginsAt":249,"volume":17,"endsAt":280},{"id":"O01CT0029d1e2561","beginsAt":365,"volume":17,"endsAt":371},{"id":"O01CT0029d1e2591","beginsAt":539,"volume":17,"endsAt":571},{"id":"O01CT0029d1e2693","beginsAt":1065,"volume":17,"endsAt":1071},{"id":"O01CT0029d1e2612","beginsAt":761,"volume":17,"endsAt":785},{"id":"O01CT0029d1e2642","beginsAt":947,"volume":17,"endsAt":982},{"id":"O01CT0029d1e456","beginsAt":103,"volume":5,"endsAt":140},{"id":"O01CT0029d1e497","beginsAt":975,"volume":5,"endsAt":1014},{"id":"O01CT0029d1e507","beginsAt":1015,"volume":5,"endsAt":1016},{"id":"O01CT0029d1e528","beginsAt":1049,"volume":5,"endsAt":1062},{"id":"O01CT0029d1e446","beginsAt":49,"volume":5,"endsAt":102},{"id":"O01CT0029d1e436","beginsAt":5,"volume":5,"endsAt":48},{"id":"O01CT0029d1e467","beginsAt":141,"volume":5,"endsAt":202},{"id":"O01CT0029d1e477","beginsAt":203,"volume":5,"endsAt":877},{"id":"O01CT0029d1e517","beginsAt":1017,"volume":5,"endsAt":1047},{"id":"O01CT0029d1e487","beginsAt":877,"volume":5,"endsAt":974},{"id":"O01CT0029d1e538","beginsAt":1063,"volume":5,"endsAt":1087},{"id":"O01CT0029d1e2815","beginsAt":243,"volume":18,"endsAt":335},{"id":"O01CT0029d1e2876","beginsAt":473,"volume":18,"endsAt":482},{"id":"O01CT0029d1e2774","beginsAt":173,"volume":18,"endsAt":195},{"id":"O01CT0029d1e2764","beginsAt":133,"volume":18,"endsAt":172},{"id":"O01CT0029d1e2886","beginsAt":483,"volume":18,"endsAt":519},{"id":"O01CT0029d1e2734","beginsAt":21,"volume":18,"endsAt":91},{"id":"O01CT0029d1e2703","beginsAt":5,"volume":18,"endsAt":10},{"id":"O01CT0029d1e2713","volumeEnd":18,"beginsAt":11,"volume":20,"endsAt":14},{"id":"O01CT0029d1e2724","beginsAt":17,"volume":18,"endsAt":19},{"id":"O01CT0029d1e2835","beginsAt":357,"volume":18,"endsAt":360},{"id":"O01CT0029d1e2846","beginsAt":361,"volume":18,"endsAt":380},{"id":"O01CT0029d1e2795","beginsAt":211,"volume":18,"endsAt":224},{"id":"O01CT0029d1e2805","beginsAt":225,"volume":18,"endsAt":241},{"id":"O01CT0029d1e2785","beginsAt":197,"volume":18,"endsAt":210},{"id":"O01CT0029d1e2744","beginsAt":93,"volume":18,"endsAt":109},{"id":"O01CT0029d1e2866","beginsAt":413,"volume":18,"endsAt":472},{"id":"O01CT0029d1e2856","beginsAt":381,"volume":18,"endsAt":412},{"id":"O01CT0029d1e2754","beginsAt":111,"volume":18,"endsAt":131},{"id":"O01CT0029d1e2825","beginsAt":337,"volume":18,"endsAt":355},{"id":"O01CT0029d1e1697","beginsAt":827,"volume":12,"endsAt":957},{"id":"O01CT0029d1e1646","beginsAt":605,"volume":12,"endsAt":610},{"id":"O01CT002901MS37","beginsAt":247,"volume":12,"endsAt":250},{"id":"O01CT0029d1e1636","beginsAt":573,"volume":12,"endsAt":603},{"id":"O01CT0029d1e1717","beginsAt":975,"volume":12,"endsAt":1013},{"id":"O01CT0029d1e1554","beginsAt":303,"volume":12,"endsAt":329},{"id":"O01CT0029d1e1493","beginsAt":141,"volume":12,"endsAt":167},{"id":"O01CT0029d1e1544","beginsAt":273,"volume":12,"endsAt":302},{"id":"O01CT0029d1e1432","beginsAt":9,"volume":12,"endsAt":58},{"id":"O01CT0029d1e1666","beginsAt":663,"volume":12,"endsAt":769},{"id":"O01CT0029d1e1443","beginsAt":59,"volume":12,"endsAt":69},{"id":"O01CT0029d1e1605","beginsAt":467,"volume":12,"endsAt":499},{"id":"O01CT0029d1e1656","beginsAt":611,"volume":12,"endsAt":662},{"id":"O01CT0029d1e1595","beginsAt":419,"volume":12,"endsAt":466},{"id":"O01CT0029d1e1585","beginsAt":387,"volume":12,"endsAt":418},{"id":"O01CT0029d1e1707","beginsAt":959,"volume":12,"endsAt":974},{"id":"O01CT0029d1e1727","beginsAt":1015,"volume":12,"endsAt":1028},{"id":"O01CT0029d1e1463","beginsAt":91,"volume":12,"endsAt":122},{"id":"O01CT0029d1e1514","beginsAt":181,"volume":12,"endsAt":245},{"id":"O01CT0029d1e1565","beginsAt":331,"volume":12,"endsAt":370},{"id":"O01CT0029d1e1453","beginsAt":71,"volume":12,"endsAt":90},{"id":"O01CT0029d1e1504","beginsAt":169,"volume":12,"endsAt":179},{"id":"O01CT0029d1e1676","beginsAt":771,"volume":12,"endsAt":810},{"id":"O01CT0029d1e1615","beginsAt":502,"volume":12,"endsAt":524},{"id":"O01CT0029d1e1687","beginsAt":811,"volume":12,"endsAt":825},{"id":"O01CT0029d1e1626","beginsAt":525,"volume":12,"endsAt":572},{"id":"O01CT0029d1e1483","beginsAt":129,"volume":12,"endsAt":139},{"id":"O01CT0029d1e1534","beginsAt":261,"volume":12,"endsAt":271},{"id":"O01CT0029d1e1524","beginsAt":251,"volume":12,"endsAt":259},{"id":"O01CT0029d1e1473","beginsAt":123,"volume":12,"endsAt":127},{"id":"O01CT0029d1e1575","beginsAt":371,"volume":12,"endsAt":386},{"id":"O01CT0029d1e1249","beginsAt":7,"volume":11,"endsAt":75},{"id":"O01CT00292DB68035","beginsAt":250,"volume":11,"endsAt":253,"title":["རྡོ་རྗེ་ཉི་མ་སོགས་ཀྱི་དོན་གྱི་མཐའ་གཅོད་ཞིབ་བཤད།"]},{"id":"O01CT0029d1e1321","beginsAt":355,"volume":11,"endsAt":383},{"id":"O01CT0029d1e1300","beginsAt":259,"volume":11,"endsAt":276},{"id":"O01CT00292DB68034","beginsAt":253,"volume":11,"endsAt":258,"title":["ཀྱཻ་རྡོ་རྗེའི་རྫོགས་རིམ་སྒྲོན་མ་གཅིག་པའི་ཁྲིད་ཡིག་ཡེ་ཤེས་རབ་གསལ།"]},{"id":"O01CT0029d1e1260","beginsAt":77,"volume":11,"endsAt":107},{"id":"O01CT0029d1e1280","beginsAt":183,"volume":11,"endsAt":231},{"id":"O01CT0029d1e1412","beginsAt":761,"volume":11,"endsAt":804},{"id":"O01CT00292DB68093","beginsAt":276,"volume":11,"endsAt":282,"title":["ཕྱག་རྒྱ་བཞིའི་སྙིང་པོའི་བྱིན་རླབས།"]},{"id":"O01CT0029d1e1341","beginsAt":431,"volume":11,"endsAt":445},{"id":"O01CT0029d1e1331","beginsAt":383,"volume":11,"endsAt":427},{"id":"O01CT0029d1e1270","beginsAt":111,"volume":11,"endsAt":181},{"id":"O01CT0029d1e1402","beginsAt":731,"volume":11,"endsAt":760},{"id":"O01CT0029d1e1310","beginsAt":283,"volume":11,"endsAt":354},{"id":"O01CT0029d1e1361","beginsAt":465,"volume":11,"endsAt":657},{"id":"O01CT0029d1e1290","beginsAt":233,"volume":11,"endsAt":250},{"id":"O01CT0029d1e1392","beginsAt":721,"volume":11,"endsAt":730},{"id":"O01CT0029d1e1351","beginsAt":447,"volume":11,"endsAt":464},{"id":"O01CT0029d1e1422","beginsAt":805,"volume":11,"endsAt":864},{"id":"O01CT0029d1e1382","beginsAt":681,"volume":11,"endsAt":720},{"id":"O01CT0029d1e1371","beginsAt":659,"volume":11,"endsAt":678},{"id":"O01CT0029d1e375","beginsAt":769,"volume":4,"endsAt":818},{"id":"O01CT0029d1e345","beginsAt":385,"volume":4,"endsAt":729},{"id":"O01CT0029d1e395","beginsAt":857,"volume":4,"endsAt":899},{"id":"O01CT0029d1e334","beginsAt":123,"volume":4,"endsAt":381},{"id":"O01CT0029d1e324","beginsAt":5,"volume":4,"endsAt":123},{"id":"O01CT0029d1e365","beginsAt":745,"volume":4,"endsAt":767},{"id":"O01CT0029d1e426","beginsAt":917,"volume":4,"endsAt":945},{"id":"O01CT0029d1e406","beginsAt":901,"volume":4,"endsAt":910},{"id":"O01CT0029d1e385","beginsAt":819,"volume":4,"endsAt":855},{"id":"O01CT0029d1e355","beginsAt":731,"volume":4,"endsAt":743},{"id":"O01CT0029d1e416","beginsAt":911,"volume":4,"endsAt":916},{"id":"O01CT0029d1e2449","beginsAt":7,"volume":16,"endsAt":14},{"id":"O01CT0029d1e2459","beginsAt":15,"volume":16,"endsAt":341},{"id":"O01CT0029d1e2469","beginsAt":343,"volume":16,"endsAt":467},{"id":"O01CT0029d1e2480","beginsAt":469,"volume":16,"endsAt":753},{"id":"O01CT0029d1e1016","beginsAt":477,"volume":8,"endsAt":699},{"id":"O01CT0029d1e1046","beginsAt":751,"volume":8,"endsAt":766},{"id":"O01CT0029d1e1036","beginsAt":735,"volume":8,"endsAt":750},{"id":"O01CT0029d1e985","beginsAt":5,"volume":8,"endsAt":353},{"id":"O01CT0029d1e1005","beginsAt":371,"volume":8,"endsAt":475},{"id":"O01CT0029d1e995","beginsAt":355,"volume":8,"endsAt":369},{"id":"O01CT0029d1e1026","beginsAt":701,"volume":8,"endsAt":733},{"id":"O01CT0029d1e1056","beginsAt":5,"volume":9,"endsAt":42},{"id":"O01CT0029d1e1066","beginsAt":43,"volume":9,"endsAt":879},{"id":"O01CT0029d1e3496","beginsAt":7,"volume":22,"endsAt":579},{"id":"O01CT0029d1e3506","beginsAt":581,"volume":22,"endsAt":621},{"id":"O01CT0029d1e3517","beginsAt":623,"volume":22,"endsAt":700},{"id":"O01CT0029d1e3527","beginsAt":703,"volume":22,"endsAt":704},{"id":"O01CT0029d1e3537","beginsAt":7,"volume":23,"endsAt":275},{"id":"O01CT0029d1e1219","beginsAt":687,"volume":10,"endsAt":711},{"id":"O01CT0029d1e1127","beginsAt":483,"volume":10,"endsAt":511},{"id":"O01CT0029d1e1148","beginsAt":551,"volume":10,"endsAt":590},{"id":"O01CT0029d1e1138","beginsAt":513,"volume":10,"endsAt":550},{"id":"O01CT0029d1e1209","beginsAt":669,"volume":10,"endsAt":686},{"id":"O01CT0029d1e1178","beginsAt":625,"volume":10,"endsAt":649},{"id":"O01CT0029d1e1117","beginsAt":411,"volume":10,"endsAt":481},{"id":"O01CT0029d1e1239","beginsAt":723,"volume":10,"endsAt":737},{"id":"O01CT0029d1e1087","beginsAt":113,"volume":10,"endsAt":185},{"id":"O01CT0029d1e1158","beginsAt":591,"volume":10,"endsAt":613},{"id":"O01CT0029d1e1188","beginsAt":651,"volume":10,"endsAt":660},{"id":"O01CT0029d1e1229","beginsAt":713,"volume":10,"endsAt":721},{"id":"O01CT0029d1e1077","beginsAt":9,"volume":10,"endsAt":113},{"id":"O01CT0029d1e1097","beginsAt":187,"volume":10,"endsAt":243},{"id":"O01CT0029d1e1168","beginsAt":615,"volume":10,"endsAt":624},{"id":"O01CT0029d1e1107","beginsAt":245,"volume":10,"endsAt":409},{"id":"O01CT0029d1e1199","beginsAt":661,"volume":10,"endsAt":668},{"id":"O01CT0029d1e2408","beginsAt":5,"volume":15,"endsAt":746},{"id":"O01CT0029d1e2419","beginsAt":747,"volume":15,"endsAt":1078},{"id":"O01CT0029d1e2429","beginsAt":1079,"volume":15,"endsAt":1142},{"id":"O01CT0029d1e2439","beginsAt":1143,"volume":15,"endsAt":1240},{"id":"O01CT0029d1e162","beginsAt":585,"volume":2,"endsAt":601},{"id":"O01CT0029d1e80","beginsAt":183,"volume":2,"endsAt":223},{"id":"O01CT0029d1e131","beginsAt":537,"volume":2,"endsAt":552},{"id":"O01CT0029d1e243","beginsAt":813,"volume":2,"endsAt":826},{"id":"O01CT0029d1e294","beginsAt":985,"volume":2,"endsAt":986},{"id":"O01CT0029d1e202","beginsAt":715,"volume":2,"endsAt":723},{"id":"O01CT0029d1e182","beginsAt":623,"volume":2,"endsAt":659},{"id":"O01CT0029d1e702DB672302DB67231","beginsAt":9,"volume":2,"endsAt":182},{"id":"O01CT0029d1e141","beginsAt":553,"volume":2,"endsAt":570},{"id":"O01CT0029d1e263","beginsAt":835,"volume":2,"endsAt":869},{"id":"O01CT0029d1e172","beginsAt":603,"volume":2,"endsAt":621},{"id":"O01CT0029d1e284","beginsAt":969,"volume":2,"endsAt":983},{"id":"O01CT0029d1e101","beginsAt":233,"volume":2,"endsAt":372},{"id":"O01CT0029d1e27300PD10374800PD103750","beginsAt":871,"volume":2,"endsAt":947},{"id":"O01CT0029d1e192","beginsAt":661,"volume":2,"endsAt":713},{"id":"O01CT0029d1e273","beginsAt":965,"volume":2,"endsAt":967},{"id":"O01CT0029d1e121","beginsAt":389,"volume":2,"endsAt":535},{"id":"O01CT0029d1e233","beginsAt":807,"volume":2,"endsAt":812},{"id":"O01CT0029d1e70","beginsAt":182,"volume":2,"endsAt":182},{"id":"O01CT0029d1e212","beginsAt":725,"volume":2,"endsAt":795},{"id":"O01CT0029d1e151","beginsAt":571,"volume":2,"endsAt":583},{"id":"O01CT0029d1e253","beginsAt":829,"volume":2,"endsAt":834},{"id":"O01CT0029d1e111","beginsAt":385,"volume":2,"endsAt":388},{"id":"O01CT0029d1e90","beginsAt":225,"volume":2,"endsAt":231},{"id":"O01CT0029d1e27300PD10374800PD103749","beginsAt":949,"volume":2,"endsAt":964},{"id":"O01CT0029d1e223","beginsAt":797,"volume":2,"endsAt":805},{"id":"O01CT0029d1e1012DB674412DB67442","beginsAt":373,"volume":2,"endsAt":384},{"id":"O01CT0029d1e304","beginsAt":7,"volume":3,"endsAt":556},{"id":"O01CT0029d1e314","beginsAt":557,"volume":3,"endsAt":878},{"id":"O01CT0029d1e2937","beginsAt":181,"volume":20,"endsAt":266},{"id":"O01CT0029d1e3090","beginsAt":717,"volume":20,"endsAt":728},{"id":"O01CT0029d1e3110","beginsAt":741,"volume":20,"endsAt":775},{"id":"O01CT0029d1e3079","beginsAt":683,"volume":20,"endsAt":709},{"id":"O01CT0029d1e2917","beginsAt":55,"volume":20,"endsAt":89},{"id":"O01CT0029d1e3039","beginsAt":633,"volume":20,"endsAt":637},{"id":"O01CT0029d1e2947","beginsAt":267,"volume":20,"endsAt":296},{"id":"O01CT0029d1e2896","beginsAt":7,"volume":20,"endsAt":26},{"id":"O01CT002901MS316","beginsAt":629,"volume":20,"endsAt":631},{"id":"O01CT002901MS353","beginsAt":711,"volume":20,"endsAt":715},{"id":"O01CT0029d1e3130","beginsAt":781,"volume":20,"endsAt":831},{"id":"O01CT0029d1e2968","beginsAt":415,"volume":20,"endsAt":438},{"id":"O01CT0029d1e3100","beginsAt":733,"volume":20,"endsAt":740},{"id":"O01CT0029d1e2907","beginsAt":27,"volume":20,"endsAt":54},{"id":"O01CT0029d1e2988","beginsAt":469,"volume":20,"endsAt":564},{"id":"O01CT0029d1e3018","beginsAt":597,"volume":20,"endsAt":606},{"id":"O01CT0029d1e3120","beginsAt":777,"volume":20,"endsAt":779},{"id":"O01CT0029d1e3049","beginsAt":639,"volume":20,"endsAt":652},{"id":"O01CT0029d1e2927","beginsAt":91,"volume":20,"endsAt":179},{"id":"O01CT0029d1e2957","beginsAt":297,"volume":20,"endsAt":414},{"id":"O01CT0029d1e2978","beginsAt":437,"volume":20,"endsAt":467},{"id":"O01CT0029d1e3008","beginsAt":581,"volume":20,"endsAt":596},{"id":"O01CT0029d1e3029","beginsAt":607,"volume":20,"endsAt":631},{"id":"O01CT002901MS338","beginsAt":663,"volume":20,"endsAt":681},{"id":"O01CT0029d1e2998","beginsAt":565,"volume":20,"endsAt":580},{"id":"O01CT0029d1e3059","beginsAt":653,"volume":20,"endsAt":662},{"id":"O01CT002901MS503","beginsAt":729,"volume":20,"endsAt":732},{"id":"O01CT0029d1e3374","beginsAt":869,"volume":21,"endsAt":874},{"id":"O01CT0029d1e3435","beginsAt":951,"volume":21,"endsAt":956},{"id":"O01CT0029d1e3191","beginsAt":309,"volume":21,"endsAt":402},{"id":"O01CT002901MS585","beginsAt":957,"volume":21,"endsAt":959},{"id":"O01CT0029d1e3486","beginsAt":1153,"volume":21,"endsAt":1165},{"id":"O01CT0029d1e3466","beginsAt":973,"volume":21,"endsAt":979},{"id":"O01CT0029d1e3384","beginsAt":875,"volume":21,"endsAt":878},{"id":"O01CT0029d1e3151","beginsAt":131,"volume":21,"endsAt":256},{"id":"O01CT0029d1e3212","beginsAt":545,"volume":21,"endsAt":563},{"id":"O01CT0029d1e3445","beginsAt":961,"volume":21,"endsAt":965},{"id":"O01CT0029d1e3476","beginsAt":981,"volume":21,"endsAt":1152},{"id":"O01CT0029d1e3232","beginsAt":581,"volume":21,"endsAt":585},{"id":"O01CT0029d1e3242","beginsAt":587,"volume":21,"endsAt":600},{"id":"O01CT0029d1e3140","beginsAt":11,"volume":21,"endsAt":130},{"id":"O01CT0029d1e3222","beginsAt":565,"volume":21,"endsAt":579},{"id":"O01CT0029d1e3161","beginsAt":257,"volume":21,"endsAt":276},{"id":"O01CT0029d1e3303","beginsAt":705,"volume":21,"endsAt":711},{"id":"O01CT0029d1e3171","beginsAt":279,"volume":21,"endsAt":287},{"id":"O01CT0029d1e3201","beginsAt":403,"volume":21,"endsAt":543},{"id":"O01CT0029d1e3405","beginsAt":905,"volume":21,"endsAt":923},{"id":"O01CT0029d1e3252","beginsAt":601,"volume":21,"endsAt":620},{"id":"O01CT0029d1e3273","beginsAt":641,"volume":21,"endsAt":652},{"id":"O01CT0029d1e3354","beginsAt":859,"volume":21,"endsAt":868},{"id":"O01CT0029d1e3283","beginsAt":653,"volume":21,"endsAt":664},{"id":"O01CT0029d1e3313","beginsAt":713,"volume":21,"endsAt":809},{"id":"O01CT0029d1e3334","beginsAt":815,"volume":21,"endsAt":846},{"id":"O01CT0029d1e3415","beginsAt":925,"volume":21,"endsAt":932},{"id":"O01CT0029d1e3262","beginsAt":621,"volume":21,"endsAt":639},{"id":"O01CT0029d1e3181","beginsAt":289,"volume":21,"endsAt":307},{"id":"O01CT0029d1e3323","beginsAt":811,"volume":21,"endsAt":814},{"id":"O01CT0029d1e3344","beginsAt":847,"volume":21,"endsAt":858},{"id":"O01CT0029d1e3364","beginsAt":867,"volume":21,"endsAt":868},{"id":"O01CT0029d1e3395","beginsAt":879,"volume":21,"endsAt":903},{"id":"O01CT0029d1e3293","beginsAt":665,"volume":21,"endsAt":704},{"id":"O01CT0029d1e3425","beginsAt":933,"volume":21,"endsAt":949},{"id":"O01CT0029d1e3456","beginsAt":967,"volume":21,"endsAt":971}]}