{"isOutlineOf":"W1PD86474","nodes":[{"id":"O1GC9991GC1060","title":["ཀུ"]},{"id":"O1GC9991GC1045","title":["མི"]},{"id":"O1GC9991GC1011","title":["ན"]},{"id":"O1GC9991GC1049","title":["ཝི"]},{"id":"O1GC9991GC1015","title":["མ"]},{"id":"O1GC9991GC1065","title":["ཆུ"]},{"id":"O1GC9991GC1031","title":["ཁི"]},{"id":"O1GC9991GC1050","title":["ཞི"]},{"id":"O1GC9991GC1008","title":["ཏ"]},{"id":"O1GC9991GC1029","title":["ཨ"]},{"id":"O1GC9991GC1002","title":["ག"]},{"id":"O1GC9991GC1074","title":["བུ"]},{"id":"O1GC9991GC1055","title":["ལི"]},{"id":"O1GC9991GC1001","title":["ཁ"]},{"id":"O1GC9991GC1022","title":["འ"]},{"id":"O1GC9991GC1032","title":["གི"]},{"id":"O1GC9991GC1019","title":["ཝ"]},{"id":"O1GC9991GC1047","title":["ཚི"]},{"id":"O1GC9991GC1057","title":["སི"]},{"id":"O1GC9991GC1026","title":["ཤ"]},{"id":"O1GC9991GC1036","title":["ཇི"]},{"id":"O1GC9991GC1070","title":["དུ"]},{"id":"O1GC9991GC1061","title":["ཁུ"]},{"id":"O1GC9991GC1042","title":["པི"]},{"id":"O1GC9991GC1040","title":["དི"]},{"id":"O1GC9991GC1056","title":["ཤི"]},{"id":"O1GC9991GC1006","title":["ཇ"]},{"id":"O1GC9991GC1004","title":["ཅ"]},{"id":"O1GC9991GC1066","title":["ཇུ"]},{"id":"O1GC9991GC1068","title":["ཏུ"]},{"id":"O1GC9991GC1051","title":["ཟི"]},{"id":"O1GC9991GC1009","title":["ཐ"]},{"id":"O1GC9991GC1030","title":["ཀི"]},{"id":"O1GC9991GC1003","title":["ང"]},{"id":"O1GC9991GC1013","title":["ཕ"]},{"id":"O1GC9991GC1012","title":["པ"]},{"id":"O1GC9991GC1023","title":["ཡ"]},{"id":"O1GC9991GC1033","title":["ངི"]},{"id":"O1GC9991GC1039","title":["ཐི"]},{"id":"O1GC9991GC1058","title":["ཧི"]},{"id":"O1GC9991GC1027","title":["ས"]},{"id":"O1GC9991GC1037","title":["ཉི"]},{"id":"O1GC9991GC1053","title":["ཡི"]},{"id":"O1GC9991GC1043","title":["ཕི"]},{"id":"O1GC9991GC1062","title":["གུ"]},{"id":"O1GC9991GC1072","title":["པུ"]},{"id":"O1GC9991GC1041","title":["ནི"]},{"id":"O1GC9991GC1020","title":["ཞ"]},{"id":"O1GC9991GC1007","title":["ཉ"]},{"id":"O1GC9991GC1017","title":["ཚ"]},{"id":"O1GC9991GC1005","title":["ཆ"]},{"id":"O1GC9991GC1024","title":["ར"]},{"id":"O1GC9991GC1067","title":["ཉུ"]},{"id":"O1GC9991GC1044","title":["བི"]},{"id":"O1GC9991GC1071","title":["ནུ"]},{"id":"O1GC9991GC1069","title":["ཐུ"]},{"id":"O1GC9991GC1010","title":["ད"]},{"id":"O1GC9991GC1048","title":["ཛི"]},{"id":"O1GC9991GC1014","title":["བ"]},{"id":"O1GC9991GC1035","title":["ཆི"]},{"id":"O1GC9991GC1064","title":["ཅུ"]},{"id":"O1GC9991GC1028","title":["ཧ"]},{"id":"O1GC9991GC1034","title":["ཅི"]},{"id":"O1GC9991GC1059","title":["ཨི"]},{"id":"O1GC9991GC1038","title":["ཏི"]},{"id":"O1GC9991GC1075","title":["མུ"]},{"id":"O1GC9991GC1054","title":["རི"]},{"id":"O1GC9991GC1063","title":["ངུ"]},{"id":"O1GC9991GC1073","title":["ཕུ"]},{"id":"O1GC9991GC1021","title":["ཟ"]},{"id":"O1GC9991GC1000","title":["ཀ"]},{"id":"O1GC9991GC1052","title":["འི"]},{"id":"O1GC9991GC1018","title":["ཛ"]},{"id":"O1GC9991GC1046","title":["ཙི"]},{"id":"O1GC9991GC1016","title":["ཙ"]},{"id":"O1GC9991GC1025","title":["ལ"]}]}