{"isOutlineOf":"W27313","nodes":[{"id":"O1LS55931PD110156","beginsAt":102,"volume":2,"endsAt":142,"title":["འཕགས་པ་གནས་བརྟན་པ་རྣམས་ཀྱི་མདོ་སྡེའི་སྡེ་སྣོད་བསྡུས་པ་ལས། ཕྲན་ཚེགས་ཀྱི་མདོ་ཕྲན་གཉིས་པ་ཆོས་ཀྱི་ཚིགས་སུ་བཅད་པ།"]},{"id":"O1LS55931PD110161","beginsAt":218,"volume":2,"endsAt":231,"title":["བྱ་ལེན་མ་མངོན་པར་ཤེས་པའི་ཟློས་གར།"]},{"id":"O1LS55931PD110160","beginsAt":214,"volume":2,"endsAt":217,"title":["དཔལ་ནག་པོའི་གླུ་ལས་ལེའུ་བཅུ་གཉིས་པ་དད་པའི་རྣལ་འབྱོར།"]},{"id":"O1LS55931PD110158","beginsAt":195,"volume":2,"endsAt":199,"title":["རི་བོ་ཧི་མ་ལའི་བསྟན་བཅོས།"]},{"id":"O1LS55931PD110159","beginsAt":200,"volume":2,"endsAt":213,"title":["དགེ་འདུན་ཆོས་འཕེལ་གྱི་སྙན་རྩོམ་ཐོར་བུ།"]},{"id":"O1LS55931PD110157","beginsAt":142,"volume":2,"endsAt":195,"title":["དབུ་མའི་ཟབ་གནད་སྙིང་པོར་དྲིལ་བའི་ལེགས་བཤད་ཀླུ་སྒྲུབ་དགོངས་རྒྱན།"]},{"id":"O1LS55931PD110152","beginsAt":8,"volume":2,"endsAt":44,"title":["སིངྒལའི་ལོ་རྒྱུས་སྐོར།"]},{"id":"O1LS55931PD110154","beginsAt":56,"volume":2,"endsAt":84,"title":["མུ་སྟེགས་ཀྱི་ཆོས་ལུགས།"]},{"id":"O1LS55931PD110153","beginsAt":45,"volume":2,"endsAt":55,"title":["སྔོན་དུས་བོད་པ་རྣམས་ཀྱི་གནས་སྐབས་དང་ཚུལ་ལུགས་ཅི་ལྟར་ཡོད་ལུགས་སྐོར།"]},{"id":"O1LS55931PD110155","beginsAt":85,"volume":2,"endsAt":101,"title":["མཇུག་རྩོམ།"]},{"id":"O1LS55931PD110151","beginsAt":7,"volume":2,"endsAt":101,"title":["རྒྱལ་ཁམས་རིག་པས་བསྐོར་བའི་གཏམ་རྒྱུད་གསེར་གྱི་ཐང་མ། ༼སྨད་ཆ།༽"]},{"id":"O1LS55931PD110150","beginsAt":6,"volume":2,"endsAt":6,"title":["དགེ་འདུན་ཆོས་འཕེལ་གྱི་གསུང་རྩོམ། དེབ་གཉིས་པའི་དཀར་ཆག"]},{"id":"O1LS55931PD110149","beginsAt":3,"volume":2,"endsAt":243},{"id":"O1LS55931PD110172","beginsAt":110,"volume":3,"endsAt":158,"title":["བོད་ཆེན་པོའི་སྲིད་ལུགས་དང་འབྲེལ་བའི་རྒྱལ་རབས་དེབ་ཐེར་དཀར་པོ།"]},{"id":"O1LS55931PD110166","beginsAt":32,"volume":3,"endsAt":65,"title":["བཙན་པོ་ཁྲི་སྲོང་ལྡེའུ་བཙན་སོགས་ཀྱི་སྐོར།"]},{"id":"O1LS55931PD110165","beginsAt":9,"volume":3,"endsAt":32,"title":["བཙན་པོ་སྲོང་བཙན་སྒམ་པོ་སོགས་ཀྱི་སྐོར།"]},{"id":"O1LS55931PD110167","beginsAt":65,"volume":3,"endsAt":68,"title":["ཐང་ཧྲུའུ་ལེའུ་བརྒྱ་དང་ཉེད་གཉིས་པ་དང་། ཟུའི་གུར་གྱི་རྒྱལ་རབས་ལེའུ་གྱ་གསུམ་པའི་ནང་འཁོད་པའི་བོད་ཀྱི་ལོ་རྒྱུས་།"]},{"id":"O1LS55931PD110164","beginsAt":8,"volume":3,"endsAt":8,"title":["རྒྱའི་ལོ་རྒྱུས་ལས་བྱུང་བའི་བོད་ཀྱི་རྒྱལ་རབས་སྐོར།"]},{"id":"O1LS55931PD110173","beginsAt":158,"volume":3,"endsAt":162,"title":["དེབ་དཀར་དུ་འཁོད་པ་དང་མ་འཁོད་པའི་ཚིགས་སུ་བཅད་པ་དང། ལོ་ཚིགས་རེ་འགའི་གནད་དོན་དོགས་དཔྱོད་དཔྱད་གཞི།"]},{"id":"O1LS55931PD110176","beginsAt":279,"volume":3,"endsAt":281,"title":["དགེ་འདུན་ཆོས་འཕེལ་གྱིས་བསྒྱུར་བ་དང་བརྩམ་པ་དངོས་སུ་བཞུགས་ཡོད་མེད་ཡོངས་ཀྱི་ཐོ་ཡིག"]},{"id":"O1LS55931PD110163","title":["དགེ་འདུན་ཆོས་འཕེལ་གྱི་གསུང་རྩོམ། དེབ་གསུམ་པའི་དཀར་ཆག"]},{"id":"O1LS55931PD110175","beginsAt":184,"volume":3,"endsAt":276,"title":["ལེགས་སྦྱར་བང་མཛོད།"]},{"id":"O1LS55931PD110169","beginsAt":69,"volume":3,"endsAt":86,"title":["༼ཀ༽ཏུན་ཧོང་ནས་ཐོན་པའི་བོད་ཀྱི་ལོ་རྒྱུས་ཡིག་ཆ།"]},{"id":"O1LS55931PD110170","beginsAt":86,"volume":3,"endsAt":94,"title":["༼ཁ༽དགེ་འདུན་ཆོས་འཕེལ་གྱིས་གོ་བདེར་མཛད་པའི་ཏུན་ཧོང་ཡིག་ཆ།"]},{"id":"O1LS55931PD110171","beginsAt":94,"volume":3,"endsAt":110,"title":["༼ག༽དགེ་འདུན་ཆོས་འཕེལ་གྱིས་གོ་བདེར་མཛད་པའི་ཏུན་ཧོང་ཡིག་ཆ།"]},{"id":"O1LS55931PD110168","beginsAt":68,"volume":3,"endsAt":68,"title":["དགེ་འདུན་ཆོས་འཕེལ་གྱིས་བསྡུ་རུབ་གནང་བ་ཏུན་ཧོང་ཡིག་ཆ།"]},{"id":"O1LS55931PD110174","beginsAt":163,"volume":3,"endsAt":183,"title":["རྒྱ་གར་གྱི་གནས་ཆེན་ཁག་ལ་བགྲོད་པའི་ལམ་ཡིག།"]},{"id":"O1LS55931PD110162","beginsAt":3,"volume":3,"endsAt":288},{"id":"O1LS55931PD110134","beginsAt":12,"volume":1,"endsAt":12,"title":["དགེ་འདུན་ཆོས་འཕེལ་གྱི་གསུང་རྩོམ། དེབ་དང་པོའི་དཀར་ཆག"]},{"id":"O1LS55931PD110133","beginsAt":10,"volume":1,"endsAt":12,"title":["དགེ་འདུན་ཆོས་འཕེལ་གྱི་ལོ་རྒྱུས་མདོར་བསྡུས།"]},{"id":"O1LS55931PD110141","beginsAt":87,"volume":1,"endsAt":125,"title":["སྐྱེས་པ་བུད་མེད་བཟའ་བཏུང་ཡོ་བྱད་སོགས་ཀྱི་སྐོར།"]},{"id":"O1LS55931PD110146","beginsAt":165,"volume":1,"endsAt":189,"title":["གུཔྟའི་རྒྱལ་བརྒྱུད།"]},{"id":"O1LS55931PD110137","beginsAt":33,"volume":1,"endsAt":41,"title":["རྒྱ་གར་གྱི་ཡུལ་སྤྱིའི་ཆགས་ཚུལ་དང་མིང་བཏགས་ཚུལ།"]},{"id":"O1LS55931PD110136","beginsAt":14,"volume":1,"endsAt":33,"title":["ཐོག་མར་ལྷ་ས་ནས་ཕེབས་ཐོན་མཛད་པའི་ཚུལ།"]},{"id":"O1LS55931PD110144","beginsAt":151,"volume":1,"endsAt":159,"title":["བོད་ཡིག་གི་སྒྲ་སྦྱོར་སྐོར།"]},{"id":"O1LS55931PD110148","beginsAt":206,"volume":1,"endsAt":226,"title":["སངས་རྒྱས་འདས་རྗེས་ཀྱི་ལོ་བརྒྱ་ཕྲག་བཅུ་དྲུག་ནས་ད་བར།"]},{"id":"O1LS55931PD110138","beginsAt":41,"volume":1,"endsAt":54,"title":["རྒྱ་གར་གྱི་ཡུལ་གྱི་མིང་བཏགས་ཚུལ།"]},{"id":"O1LS55931PD110147","beginsAt":190,"volume":1,"endsAt":205,"title":["པཱ་ལའི་རྒྱལ་བརྒྱུད་སྐབས།"]},{"id":"O1LS55931PD110142","beginsAt":126,"volume":1,"endsAt":136,"title":["ཤིང་དང་མེ་ཏོག་སོགས་ཀྱི་ངོས་འཛིན་དང་ངོས་ཇི་ལྟར་འཕྲོད་ཚུལ།"]},{"id":"O1LS55931PD110145","beginsAt":159,"volume":1,"endsAt":165,"title":["ཆོས་རྒྱལ་མྱ་ངན་མེད་ཀྱི་ཡི་གེ་རི་ན་ག་རེའི་བྲག་ངོས་ལ་བརྐོས་པ།"]},{"id":"O1LS55931PD110140","beginsAt":58,"volume":1,"endsAt":87,"title":["སྔོན་གྱི་གནས་ཡུལ་གྲགས་ཅན་རྣམས་ཇི་ལྟར་ཡོད་ཚུལ།"]},{"id":"O1LS55931PD110143","beginsAt":136,"volume":1,"endsAt":151,"title":["སྔོན་དང་ད་ལྟའི་བར་ཡུལ་སོ་སོའི་ཡིག་རིགས།"]},{"id":"O1LS55931PD110139","beginsAt":54,"volume":1,"endsAt":57,"title":["བྱང་ཕྱོགས་ཀྱི་གངས་རི་དང་དེ་ལས་འཕྲོས་པའི་དོགས་དཔྱོད།"]},{"id":"O1LS55931PD110135","beginsAt":13,"volume":1,"endsAt":226,"title":["རྒྱལ་ཁམས་རིག་པས་བསྐོར་བའི་གཏམ་རྒྱུད་གསེར་གྱི་ཐང་མ། ༼སྟོད་ཆ།༽"]},{"id":"O1LS55931PD110132","beginsAt":3,"volume":1,"endsAt":238}]}