{"isOutlineOf":"W20840","nodes":[{"id":"O2CN3172CN3292CN12342CN1286","beginsAt":42,"volume":1,"endsAt":45},{"id":"O2CN3172CN3262CN12312CN1283","beginsAt":24,"volume":1,"endsAt":30},{"id":"O2CN3172CN3212CN12262CN1278","beginsAt":9,"volume":1,"endsAt":10},{"id":"O2CN3172CN3312CN12362CN1288","beginsAt":46,"volume":1,"endsAt":50},{"id":"O2CN3172CN3342CN12392CN1291","beginsAt":53,"volume":1,"endsAt":55},{"id":"O2CN3172CN3242CN12292CN1281","beginsAt":16,"volume":1,"endsAt":19},{"id":"O2CN3172CN1310","beginsAt":5,"volume":1,"endsAt":6},{"id":"O2CN3172CN12582CN1276","beginsAt":3,"volume":1,"endsAt":4},{"id":"O2CN3172CN3202CN12252CN1277","beginsAt":7,"volume":1,"endsAt":8},{"id":"O2CN3172CN3352CN12402CN1292","beginsAt":57,"volume":1,"endsAt":165},{"id":"O2CN3172CN3302CN12352CN1287","beginsAt":45,"volume":1,"endsAt":46},{"id":"O2CN3172CN3232CN12282CN1280","beginsAt":11,"volume":1,"endsAt":15},{"id":"O2CN3172CN3282CN12332CN1285","beginsAt":33,"volume":1,"endsAt":42},{"id":"O2CN3172CN3222CN12272CN1279","beginsAt":10,"volume":1,"endsAt":11},{"id":"O2CN3172CN3322CN12372CN1289","beginsAt":50,"volume":1,"endsAt":52},{"id":"O2CN3172CN3332CN12382CN1290","beginsAt":52,"volume":1,"endsAt":53},{"id":"O2CN3172CN3252CN12302CN1282","beginsAt":19,"volume":1,"endsAt":24},{"id":"O2CN3172CN3272CN12322CN1284","beginsAt":30,"volume":1,"endsAt":32}]}