{"volumeMap":[{"id":"I1GS66320","total":528,"num":2},{"id":"I1GS66330","total":528,"num":12},{"id":"I1GS66319","total":548,"num":1},{"id":"I1GS66323","total":540,"num":5},{"id":"I1GS66328","total":458,"num":10},{"id":"I1GS66325","total":582,"num":7},{"id":"I1GS66322","total":504,"num":4},{"id":"I1GS66327","total":502,"num":9},{"id":"I1GS66321","total":538,"num":3},{"id":"I1GS66324","total":540,"num":6},{"id":"I1GS66331","total":560,"num":13},{"id":"I1GS66329","total":456,"num":11},{"id":"I1GS66326","total":408,"num":8}],"title":["གསུང་འབུམ། འཇིགས་མེད་རིགས་པའི་བློ་གྲོས","ཚེ་ཏན་ཞབས་དྲུང་རྗེ་བཙུན་འཇིགས་མེད་རིགས་པའི་བློ་གྲོས་མཆོག་གི་གསུང་འབུམ"],"archiveInfo_status":"scanned","status":"released","hasCreator":["P1646"],"archiveInfo_vols":"13","publisherDate":"2007"}