{"volumeMap":[{"id":"I3CN446","total":0,"num":8},{"id":"I3CN444","total":0,"num":6},{"id":"I3CN449","total":0,"num":11},{"id":"I3CN450","total":0,"num":12},{"id":"I3CN442","total":0,"num":4},{"id":"I3CN445","total":0,"num":7},{"id":"I3CN440","total":0,"num":2},{"id":"I3CN447","total":0,"num":9},{"id":"I3CN439","total":0,"num":1},{"id":"I3CN441","total":0,"num":3},{"id":"I3CN443","total":0,"num":5},{"id":"I3CN448","total":0,"num":10}],"title":[null],"status":"released","archiveInfo_vols":"12","publisherLocation":"ཁམས་སྡེ་དགེ།","archiveInfo_status":"scanned","publisherDate":"2016","printType":"computerInput"}